simpletwitter/__init__.py
simpletwitter-1.2.8.dist-info/LICENCE.txt
simpletwitter-1.2.8.dist-info/METADATA
simpletwitter-1.2.8.dist-info/WHEEL
simpletwitter-1.2.8.dist-info/top_level.txt
simpletwitter-1.2.8.dist-info/RECORD
